.gitignore
.gitmodules
.pylintrc
.travis.yml
CMakeLists.txt
CONTRIBUTING.md
LICENSE
MANIFEST.in
README.md
default.nix
setup.cfg
setup.py
tox.ini
basalt/__init__.py
basalt/serialization.py
basalt/topology.py
basalt.egg-info/PKG-INFO
basalt.egg-info/SOURCES.txt
basalt.egg-info/dependency_links.txt
basalt.egg-info/not-zip-safe
basalt.egg-info/requires.txt
basalt.egg-info/top_level.txt
cmake/DartConfig.cmake
cmake/FindClangTidy.cmake
cmake/FindGoogleBenchmark.cmake
cmake/FindRocksDB.cmake
cmake/hpc-coding-conventions/.gitignore
cmake/hpc-coding-conventions/Makefile
cmake/hpc-coding-conventions/Pipfile
cmake/hpc-coding-conventions/setup.cfg
cmake/hpc-coding-conventions/cpp/.clang-format-7
cmake/hpc-coding-conventions/cpp/.clang-format-8
cmake/hpc-coding-conventions/cpp/.clang-format-9
cmake/hpc-coding-conventions/cpp/.clang-tidy
cmake/hpc-coding-conventions/cpp/.cmake-format.yaml
cmake/hpc-coding-conventions/cpp/CMakeLists.txt
cmake/hpc-coding-conventions/cpp/DevelopmentLifecycle.md
cmake/hpc-coding-conventions/cpp/Documentation.md
cmake/hpc-coding-conventions/cpp/Makefile
cmake/hpc-coding-conventions/cpp/NamingConventions.md
cmake/hpc-coding-conventions/cpp/README.md
cmake/hpc-coding-conventions/cpp/Tooling.md
cmake/hpc-coding-conventions/cpp/cmake/FindCMakeFormat.cmake
cmake/hpc-coding-conventions/cpp/cmake/FindClangFormat.cmake
cmake/hpc-coding-conventions/cpp/cmake/FindClangTidy.cmake
cmake/hpc-coding-conventions/cpp/cmake/FindPreCommit.cmake
cmake/hpc-coding-conventions/cpp/cmake/bbp-clang-format.py
cmake/hpc-coding-conventions/cpp/cmake/bbp-clang-tidy.py
cmake/hpc-coding-conventions/cpp/cmake/bbp-cmake-format.py
cmake/hpc-coding-conventions/cpp/cmake/bbp-diff-filter.py
cmake/hpc-coding-conventions/cpp/cmake/bbp-setup-pre-commit-config.py
cmake/hpc-coding-conventions/cpp/cmake/bob.cmake
cmake/hpc-coding-conventions/cpp/cmake/cpplib.py
cmake/hpc-coding-conventions/cpp/cmake/runClangFormat.cmake
cmake/hpc-coding-conventions/cpp/formatting/.gitignore
cmake/hpc-coding-conventions/cpp/formatting/CONTRIBUTING.md
cmake/hpc-coding-conventions/cpp/formatting/Makefile
cmake/hpc-coding-conventions/cpp/formatting/README.md
