Metadata-Version: 2.1
Name: basalt
Version: 0.2.9
Summary: Graph API powered by RocksDB persistent key-value store for fast storage
Home-page: UNKNOWN
Author: BlueBrain Project, EPFL
Author-email: tristan.carel@epfl.ch
License: LGPLv3
Platform: UNKNOWN
Classifier: Development Status :: 3 - Alpha
Classifier: Environment :: Console :: Curses
Classifier: Intended Audience :: Developers
Classifier: License :: OSI Approved :: GNU Lesser General Public License v3 (LGPLv3)
Classifier: Operating System :: MacOS
Classifier: Operating System :: POSIX :: Linux
Classifier: Programming Language :: C++
Classifier: Programming Language :: Python :: 3
Classifier: Programming Language :: Python :: 3.5
Classifier: Programming Language :: Python :: 3.6
Classifier: Programming Language :: Python :: 3.7
Classifier: Topic :: Database :: Database Engines/Servers
Requires-Python: >=3.5
